cliparse/__init__.py
cliparse/__main__.py
cliparse/requirements.txt
cliparse/viewer/__init__.py
cliparse/viewer/simple_table.py
cliparse-1.1.0.dist-info/LICENSE
cliparse-1.1.0.dist-info/WHEEL
cliparse-1.1.0.dist-info/METADATA
cliparse-1.1.0.dist-info/RECORD
